electf4/__init__.py
electf4/make_data.py
electf4/plot.py
electf4/tdd.py
electf4/validators.py
electf4_basicML-0.1.9.dist-info/LICENSE
electf4_basicML-0.1.9.dist-info/METADATA
electf4_basicML-0.1.9.dist-info/WHEEL
electf4_basicML-0.1.9.dist-info/top_level.txt
electf4_basicML-0.1.9.dist-info/RECORD
