Metadata-Version: 2.1
Name: electf4_basicML
Version: 0.1.9
Summary: UNKNOWN
Home-page: UNKNOWN
License: UNKNOWN
Platform: UNKNOWN
License-File: LICENSE
